Workbook

Sheet Summary
A1: Decision Platform — 30/60/90 delivery backlog
A2: Aligned to the executive deck, slide 14. Each horizon is defined by the outcome that becomes true at the end of it.
A3: Generated 24 September 2026. Story points are planning estimates, not commitments — see the capacity note below.
A5: HORIZON | B5: SUCCESS CRITERION | C5: EPICS | D5: ISSUES | E5: POINTS | F5: CRITICAL PTS
A6: By Day 30 | B6: We can reconstruct every eligible decision and its counterfactual. | C6: =COUNTIFS(Backlog!$L:$L,"D30",Backlog!$B:$B,"Epic") -> 4 | D6: =COUNTIFS(Backlog!$L:$L,"D30")-C6 -> 26 | E6: =SUMIFS(Backlog!$H:$H,Backlog!$L:$L,"D30") -> 115 | F6: =SUMIFS(Backlog!$H:$H,Backlog!$L:$L,"D30",Backlog!$I:$I,"Y") -> 102
A7: By Day 60 | B7: We can register, replay and validate a strategy without a release. | C7: =COUNTIFS(Backlog!$L:$L,"D60",Backlog!$B:$B,"Epic") -> 5 | D7: =COUNTIFS(Backlog!$L:$L,"D60")-C7 -> 28 | E7: =SUMIFS(Backlog!$H:$H,Backlog!$L:$L,"D60") -> 189 | F7: =SUMIFS(Backlog!$H:$H,Backlog!$L:$L,"D60",Backlog!$I:$I,"Y") -> 164
A8: By Day 90 | B8: We have one controlled experiment running and can produce an economic readout. | C8: =COUNTIFS(Backlog!$L:$L,"D90",Backlog!$B:$B,"Epic") -> 6 | D8: =COUNTIFS(Backlog!$L:$L,"D90")-C8 -> 35 | E8: =SUMIFS(Backlog!$H:$H,Backlog!$L:$L,"D90") -> 249 | F8: =SUMIFS(Backlog!$H:$H,Backlog!$L:$L,"D90",Backlog!$I:$I,"Y") -> 221
A9: Beyond Day 90 | B9: Scale to more decision points, open Experiment 2, begin learned strategies. | C9: =COUNTIFS(Backlog!$L:$L,"D90+",Backlog!$B:$B,"Epic") -> 1 | D9: =COUNTIFS(Backlog!$L:$L,"D90+")-C9 -> 4 | E9: =SUMIFS(Backlog!$H:$H,Backlog!$L:$L,"D90+") -> 34 | F9: =SUMIFS(Backlog!$H:$H,Backlog!$L:$L,"D90+",Backlog!$I:$I,"Y") -> 34
A10: TOTAL | C10: =SUM(C6:C9) -> 16 | D10: =SUM(D6:D9) -> 93 | E10: =SUM(E6:E9) -> 587 | F10: =SUM(F6:F9) -> 521
A13: CAPACITY CHECK — does the plan fit?
A14: Edit the blue cells. Everything else is a formula.
A15: Sprint length (weeks) | B15: 2
A16: Sprints in 90 days | B16: 6
A17: Velocity per squad per sprint (points) | B17: 30
A18: Points one squad delivers in 90 days | B18: =B16*B17 -> 180
A19: Points required for D30 + D60 + D90 (all) | B19: =E6+E7+E8 -> 553
A20: Points required for D30 + D60 + D90 (critical only) | B20: =F6+F7+F8 -> 487
A21: Squads needed — full scope | B21: =ROUND(B19/B18,1) -> 3.1
A22: Squads needed — critical scope only | B22: =ROUND(B20/B18,1) -> 2.7
A24: The deck says the mechanism is buildable inside existing platform capacity. That is true of the mechanism, not of this schedule. If only one squad is available, the 90-day outcomes need either more time or a scope cut against the Critical To Outcome column.

Sheet Backlog
A1: # | B1: Issue Type | C1: Epic | D1: Summary | E1: Description | F1: Acceptance Criteria | G1: Priority | H1: Story Points | I1: Critical To Outcome | J1: Requirement | K1: Objective | L1: Fix Version | M1: Component | N1: Team | O1: Blocked By
A2: 1 | B2: Epic | C2: Decision Evidence Layer | D2: Decision Evidence Layer | E2: Every eligible decision on the CURRENT engine emits what was chosen, what else was permitted, the probability assigned, and what the fallback would have done. This is the one capability that cannot be backfilled. | G2: P0 | J2: R8 | K2: O3 | L2: D30 | M2: Decision Runtime | N2: Payments Platform
A3: 2 | B3: Story | C3: Decision Evidence Layer | D3: Define the decision record schema | E3: As the platform, I need a single schema for every decision the engine makes, so that decisions from different decision points are comparable and joinable. | F3: • Schema covers: decision point id, strategy id and version, chosen action, permitted action set, propensity assigned to the chosen action, fallback action that would have fired, population context, timestamp, transaction and customer identifiers. • Schema is versioned and additive-only. • Reviewed and signed off by Architecture and Analytics Engineering. | G3: P0 | H3: 5 | I3: Y | J3: R8 | K3: O3 | L3: D30 | M3: Decision Runtime | N3: Payments Platform
A4: 3 | B4: Story | C4: Decision Evidence Layer | D4: Emit decision records from the routing engine (D6) | E4: As an analyst, I need every routing decision logged with its counterfactual, so that routing strategies can later be evaluated off-policy. | F4: • Every D6 decision on eligible traffic emits a record. • No change to the routing decision itself — output is byte-identical to today for a control sample of 1M transactions. • Record includes the permitted processor set and the fallback processor. | G4: P0 | H4: 8 | I4: Y | J4: R8 | K4: O3 | L4: D30 | M4: Decision Runtime | N4: Payments Platform | O4: Define the decision record schema
A5: 4 | B5: Story | C5: Decision Evidence Layer | D5: Emit decision records from the retry engine (D4.2) | E5: As an analyst, I need retry decisions logged with what else was permitted, so that retry strategies become evaluable. | F5: • Every D4.2 decision emits a record, including no-action decisions. • Retry behaviour unchanged. • Retry records link to the parent authorization attempt. | G5: P0 | H5: 8 | I5: Y | J5: R8 | K5: O3 | L5: D30 | M5: Decision Runtime | N5: Payments Platform | O5: Define the decision record schema
A6: 5 | B6: Story | C6: Decision Evidence Layer | D6: Emit decision records from credential selection (D4.1) | E6: As an analyst, I need credential selection logged with the alternative credential, so that Experiment 1 has a counterfactual to report. | F6: • Every D4.1 decision emits a record naming the credential presented and the credential not presented. • Credential values are tokenised in the record — no PAN in the event store. • Credential selection behaviour unchanged. | G6: P0 | H6: 8 | I6: Y | J6: R8 | K6: O3 | L6: D30 | M6: Decision Runtime | N6: Payments Platform | O6: Define the decision record schema
A7: 6 | B7: Story | C7: Decision Evidence Layer | D7: Assign and document propensity for deterministic strategies | E7: As an analyst, I need a stated propensity convention for deterministic strategies, so that off-policy estimators are not silently mis-specified later. | F7: • Deterministic strategies record propensity 1.0 on the chosen action and 0 on the alternatives. • Convention is documented alongside the schema, with the implications for off-policy evaluation stated. • A strategy class field distinguishes DETERMINISTIC from future stochastic classes. | G7: P0 | H7: 3 | I7: Y | J7: R8 | K7: O3 | L7: D30 | M7: Decision Runtime | N7: Payments Platform | O7: Define the decision record schema
A8: 7 | B8: Story | C8: Decision Evidence Layer | D8: Record the fallback action without executing it | E8: As the platform, I need to know what the fallback would have done, so that attribution is possible without running two flows. | F8: • Fallback resolution runs in shadow and never dispatches. • Added latency measured and within the agreed budget. • Fallback field is never null for a decision that has a registered fallback. | G8: P0 | H8: 5 | I8: Y | J8: R8 | K8: O3 | L8: D30 | M8: Decision Runtime | N8: Payments Platform | O8: Define the decision record schema
A9: 8 | B9: Story | C9: Decision Evidence Layer | D9: Persist decision records with 13-month retention | E9: As an analyst, I need at least four quarters of history, so that seasonality can be separated from effect. | F9: • Records land in the event store within 60 seconds of the decision. • 13-month retention configured and cost-modelled. • Partitioned for efficient replay by date range and decision point. | G9: P0 | H9: 5 | I9: Y | J9: R8 | K9: O3 | L9: D30 | M9: Decision Runtime | N9: Payments Platform | O9: Define the decision record schema
A10: 9 | B10: Story | C10: Decision Evidence Layer | D10: Block synthesised propensity in downstream jobs | E10: As a reviewer, I need the platform to refuse reconstructed propensity, so that an evaluated result is never quietly based on a guess. | F10: • Any job writing a propensity value for a record that did not carry one is rejected. • Rejection is logged and alerts the strategy owner. • Documented as a platform invariant, not a lint rule. | G10: P0 | H10: 3 | I10: N | J10: R8 | K10: O3 | L10: D30 | M10: Decision Runtime | N10: Payments Platform | O10: Persist decision records with 13-month retention
A11: 10 | B11: Story | C11: Decision Evidence Layer | D11: Verify record completeness against transaction volume | E11: As a reviewer, I need proof that the evidence layer is not silently dropping decisions, so that a later readout is trustworthy. | F11: • Daily reconciliation: decision records vs eligible transactions, by decision point. • Completeness at or above 99.5%. • Shortfall below threshold raises an alert with the missing population identified. | G11: P0 | H11: 5 | I11: Y | J11: R8 | K11: O3 | L11: D30 | M11: Decision Runtime | N11: Payments Platform | O11: Persist decision records with 13-month retention
A12: 11 | B12: Spike | C12: Decision Evidence Layer | D12: SPIKE: measure added latency of decision-record emission | E12: As the platform owner, I need to know what the evidence layer costs in latency before it goes to full traffic, so that the authorization path is not degraded. | F12: • p50, p95 and p99 added latency measured at production-representative volume. • Result compared against the agreed latency budget. • Recommendation on synchronous vs asynchronous emission, with the trade-off on completeness stated. | G12: P0 | H12: 3 | I12: Y | J12: R8 | K12: O3 | L12: D30 | M12: Decision Runtime | N12: Payments Platform
A13: 12 | B13: Epic | C13: Permanent Platform Holdout | D13: Permanent Platform Holdout | E13: A 2% population reserved before the first experiment runs, excluded from experiments and from exploration, with a creation date that cannot be edited. | G13: P0 | J13: R7 | K13: O2 O3 | L13: D30 | M13: Decision Runtime | N13: Payments Platform
A14: 13 | B14: Story | C14: Permanent Platform Holdout | D14: Define holdout eligibility and the assignment rule | E14: As the platform owner, I need a stated rule for who is in the holdout, so that it is defensible and stable over time. | F14: • Eligibility defined at customer level, with the population and exclusions written down. • Assignment is a deterministic hash — same customer, same answer, forever. • Rule reviewed by Analytics Engineering for representativeness against the total population. | G14: P0 | H14: 3 | I14: Y | J14: R7 | K14: O2 O3 | L14: D30 | M14: Decision Runtime | N14: Payments Platform
A15: 14 | B15: Story | C15: Permanent Platform Holdout | D15: Implement deterministic 2% holdout assignment | E15: As the platform, I need holdout membership computed the same way everywhere, so that it cannot drift between services. | F15: • Assignment implemented once and consumed by every caller. • Same customer resolves identically across regions. • Membership resolvable in under 1ms. | G15: P0 | H15: 5 | I15: Y | J15: R7 | K15: O2 O3 | L15: D30 | M15: Decision Runtime | N15: Payments Platform | O15: Define holdout eligibility and the assignment rule
A16: 15 | B16: Story | C16: Permanent Platform Holdout | D16: Exclude the holdout from experiments and from exploration | E16: As a reviewer, I need the holdout untouched by any learning activity, so that it measures the platform rather than the experiments. | F16: • Holdout members are never enrolled in any experiment. • Holdout members are never selected for exploration traffic. • An attempt to include them fails closed and raises an alert. | G16: P0 | H16: 5 | I16: Y | J16: R7 | K16: O2 O3 | L16: D30 | M16: Decision Runtime | N16: Payments Platform | O16: Implement deterministic 2% holdout assignment
A17: 16 | B17: Story | C17: Permanent Platform Holdout | D17: Persist holdout membership with an immutable creation date | E17: As a reviewer, I need to prove when the holdout was reserved, so that the claim that it pre-dates the experiments is verifiable. | F17: • Creation date recorded at first assignment and not editable by any role. • Membership history retained for the life of the platform. • Audit log for any membership change. | G17: P0 | H17: 3 | I17: Y | J17: R7 | K17: O2 O3 | L17: D30 | M17: Decision Runtime | N17: Payments Platform | O17: Implement deterministic 2% holdout assignment
A18: 17 | B18: Story | C18: Permanent Platform Holdout | D18: Holdout health report | E18: As an analyst, I need to see holdout composition and drift, so that a divergence from the general population is caught early. | F18: • Weekly report: volume, merchant mix, geography mix, card mix vs the non-holdout population. • Alerts on material composition drift. • Report retained as evidence alongside readouts. | G18: P1 | H18: 5 | I18: N | J18: R7 | K18: O2 O3 | L18: D30 | M18: Decision Runtime | N18: Payments Platform | O18: Persist holdout membership with an immutable creation date
A19: 18 | B19: Story | C19: Permanent Platform Holdout | D19: Document the holdout as a governed, non-resizable asset | E19: As the platform owner, I need a stated rule that the holdout cannot be quietly resized, so that its value is not eroded under delivery pressure. | F19: • Written policy: resizing or reconstituting the holdout requires a named approval from the platform owner. • Policy referenced in the experiment registration gates. | G19: P1 | H19: 2 | I19: N | J19: R7 | K19: O2 O3 | L19: D30 | M19: Decision Runtime | N19: Payments Platform
A20: 19 | B20: Epic | C20: Decision-Point & Capability Registry — Definition | D20: Decision-Point & Capability Registry — Definition | E20: Agree what the decision points are, what each may choose from, and what a route can actually support. Scope and schema only — the build is D60. | G20: P0 | J20: R1 | K20: O1 O5 | L20: D30 | M20: Architecture | N20: Architecture
A21: 20 | B21: Story | C21: Decision-Point & Capability Registry — Definition | D21: Catalogue the current decision points and permitted action sets | E21: As an architect, I need a written inventory of where the payment flow makes choices, so that the registry describes reality rather than an ideal. | F21: • All five current decision points documented: D4 gate, D4.1 credential, D4.2 retry, D5 authentication, D6 routing. • Permitted action set enumerated for each, as implemented today. • Gaps between documented and actual behaviour listed explicitly. | G21: P0 | H21: 5 | I21: Y | J21: R1 | K21: O1 O5 | L21: D30 | M21: Architecture | N21: Architecture
A22: 21 | B22: Story | C22: Decision-Point & Capability Registry — Definition | D22: Define the capability model | E22: As an architect, I need a model of what each route and processor can actually support, so that a strategy cannot select an option that will fail downstream. | F22: • Capability dimensions defined: credential forms accepted, authentication methods, currencies, MCCs, network tokens, retry semantics. • Model distinguishes contractual capability from technical capability. • Reviewed with Network and Processor Management. | G22: P0 | H22: 5 | I22: Y | J22: R1 | K22: O1 O5 | L22: D30 | M22: Architecture | N22: Architecture
A23: 22 | B23: Story | C23: Decision-Point & Capability Registry — Definition | D23: Agree the registry schema and versioning approach | E23: As an architect, I need the registry to be bitemporal, so that we can answer both what is true now and what was true when a decision was made. | F23: • Schema covers valid time and knowledge time. • Versioning and deprecation rules written down. • Signed off by Architecture. | G23: P0 | H23: 3 | I23: Y | J23: R1 | K23: O1 O5 | L23: D30 | M23: Architecture | N23: Architecture | O23: Catalogue the current decision points and permitted action sets
A24: 23 | B24: Spike | C24: Decision-Point & Capability Registry — Definition | D24: SPIKE: survey processor capability data availability | E24: As an architect, I need to know which capability facts we can obtain and which we will have to assert, so that the D60 verification work is correctly sized. | F24: • Each processor surveyed for available capability data and format. • Gaps listed with an estimate of effort to close. • Recommendation on which facts must be verified vs may be asserted with an expiry. | G24: P0 | H24: 5 | I24: Y | J24: R1 | K24: O1 O5 | L24: D30 | M24: Architecture | N24: Architecture | O24: Define the capability model
A25: 24 | B25: Story | C25: Decision-Point & Capability Registry — Definition | D25: Publish the registry scope decision for sign-off | E25: As the programme, I need the registry scope agreed before it is built, so that D60 is a build rather than a design. | F25: • Scope document published naming what is in and out of the first registry. • Architecture sign-off recorded. • Out-of-scope items carried to the D90+ backlog rather than dropped. | G25: P0 | H25: 2 | I25: Y | J25: R1 | K25: O1 O5 | L25: D30 | M25: Architecture | N25: Architecture | O25: Agree the registry schema and versioning approach
A26: 25 | B26: Epic | C26: Operating Model & Ownership | D26: Operating Model & Ownership | E26: The five ownership boundaries named, the exploration budget bounded, the economic objective expressed in a usable form, and the consent posture settled. | G26: P0 | J26: — | K26: O1 O4 | L26: D30 | M26: Governance | N26: Product
A27: 26 | B27: Story | C27: Operating Model & Ownership | D27: Assign and document the five ownership boundaries | E27: As the programme, I need named owners for the five decisions that bound the platform, so that they are not re-litigated every quarter. | F27: • Named owner recorded for: economic objective, exploration budget, decision-point registry, exposure authority, exploration consent. • Each owner has confirmed in writing. • Escalation path defined where two owners disagree. | G27: P0 | H27: 3 | I27: Y | J27: — | K27: O1 O4 | L27: D30 | M27: Governance | N27: Product
A28: 27 | B28: Story | C28: Operating Model & Ownership | D28: Define the exploration budget in basis points, with a ceiling | E28: As Product, I need a stated budget for what learning costs, so that exploration is a decision rather than an accident. | F28: • Budget expressed in bps of qualifying volume, per quarter. • Hard ceiling defined, above which an experiment cannot start. • Consumption tracked and reported against the budget. | G28: P0 | H28: 3 | I28: Y | J28: — | K28: O1 O4 | L28: D30 | M28: Governance | N28: Product | O28: Assign and document the five ownership boundaries
A29: 28 | B29: Story | C29: Operating Model & Ownership | D29: Define the economic objective form by pricing model | E29: As Product and Finance, I need the approval-versus-cost trade-off expressed in a form a strategy can actually consume, so that BALANCED is a real posture rather than a label. | F29: • Objective expressed as an exchange rate: bps of cost accepted per 100 bps of approval. • A value agreed separately for interchange-plus and for blended pricing. • Documented with worked examples in both directions. | G29: P0 | H29: 5 | I29: Y | J29: — | K29: O1 O4 | L29: D30 | M29: Governance | N29: Product | O29: Assign and document the five ownership boundaries
A30: 29 | B30: Story | C30: Operating Model & Ownership | D30: Legal review of exploration consent posture | E30: As the programme, I need to know whether a knowingly weaker arm on a named client needs contractual consent, so that Experiment 1 does not stop at the last gate. | F30: • Legal opinion recorded on running a deliberately degraded arm on live merchant traffic. • Position stated for existing contracts and for new ones. • If consent is required, the consent artefact and the signing path are defined. | G30: P0 | H30: 5 | I30: Y | J30: — | K30: O1 O4 | L30: D30 | M30: Governance | N30: Product | O30: Assign and document the five ownership boundaries
A31: 30 | B31: Story | C31: Operating Model & Ownership | D31: Define the experiment review forum and decision rights | E31: As the programme, I need a standing forum with stated decision rights, so that promotion and abort decisions are made rather than escalated. | F31: • Forum membership, cadence and quorum defined. • Decision rights stated: who may promote, who may abort, who may widen exposure. • First meeting scheduled. | G31: P1 | H31: 3 | I31: N | J31: — | K31: O1 O4 | L31: D30 | M31: Governance | N31: Product | O31: Assign and document the five ownership boundaries
A32: 31 | B32: Epic | C32: Strategy Registry & Artefact Lifecycle | D32: Strategy Registry & Artefact Lifecycle | E32: A strategy becomes a registered, versioned artefact with an owner, a fallback and an expiry — deployable without an engineering release. | G32: P0 | J32: R1 R14 | K32: O1 O4 | L32: D60 | M32: Control Plane | N32: Payments Platform
A33: 32 | B33: Story | C33: Strategy Registry & Artefact Lifecycle | D33: Strategy artefact schema | E33: As a strategy owner, I need a strategy to be a declared artefact rather than code, so that it can be reviewed, versioned and retired without a release. | F33: • Schema: id, version, decision point, class, population predicate, definition, fallback strategy reference, owner, expiry. • Fallback is mandatory and must reference a registered strategy. • Owner and expiry are mandatory. | G33: P0 | H33: 5 | I33: Y | J33: R1 R14 | K33: O1 O4 | L33: D60 | M33: Control Plane | N33: Payments Platform | O33: Agree the registry schema and versioning approach
A34: 33 | B34: Story | C34: Strategy Registry & Artefact Lifecycle | D34: Strategy registration API and CLI | E34: As a strategy owner, I need to register a strategy without an engineering release, so that the change cycle is days rather than quarters. | F34: • API accepts a strategy artefact and returns a registered version. • CLI wraps the API for the common path. • Registration is rejected with a specific, actionable message when a field is invalid. | G34: P0 | H34: 8 | I34: Y | J34: R1 | K34: O1 O4 | L34: D60 | M34: Control Plane | N34: Payments Platform | O34: Strategy artefact schema
A35: 34 | B35: Story | C35: Strategy Registry & Artefact Lifecycle | D35: Version immutability | E35: As a reviewer, I need a registered version to be unchangeable, so that a readout always refers to a known artefact. | F35: • A registered version cannot be edited — a change produces a new version. • Prior versions remain resolvable indefinitely. • Attempted edit is rejected and audited. | G35: P0 | H35: 5 | I35: Y | J35: R1 | K35: O1 O4 | L35: D60 | M35: Control Plane | N35: Payments Platform | O35: Strategy registration API and CLI
A36: 35 | B36: Story | C36: Strategy Registry & Artefact Lifecycle | D36: Owner and expiry enforcement | E36: As the platform owner, I need strategies to expire, so that nothing lingers unowned in the decision path. | F36: • Expiry is mandatory at registration, with a maximum of 180 days. • Warnings to the owner at 30 and 7 days. • An expired strategy stops being bindable; flows already bound to it fall back and alert. | G36: P0 | H36: 5 | I36: Y | J36: R14 | K36: O1 O4 | L36: D60 | M36: Control Plane | N36: Payments Platform | O36: Strategy registration API and CLI
A37: 36 | B37: Story | C37: Strategy Registry & Artefact Lifecycle | D37: Strategy retirement workflow | E37: As a strategy owner, I need a clean way to retire a strategy, so that losing variants do not accumulate. | F37: • Retirement blocks new bindings and reports which flows still reference the strategy. • Retirement is reversible within 30 days, then permanent. • Retired strategies remain resolvable for historical traces. | G37: P1 | H37: 5 | I37: N | J37: R14 | K37: O1 O4 | L37: D60 | M37: Control Plane | N37: Payments Platform | O37: Version immutability
A38: 37 | B38: Story | C38: Strategy Registry & Artefact Lifecycle | D38: Naming convention validation | E38: As a reviewer, I need strategy names to describe what they do, so that a trace is readable a year later. | F38: • Registration rejects opaque names such as Strategy1 or Test_A. • Convention documented with positive and negative examples. • Existing names migrated before D60 exit. | G38: P2 | H38: 2 | I38: N | J38: R1 | K38: O1 O4 | L38: D60 | M38: Control Plane | N38: Payments Platform | O38: Strategy registration API and CLI
A39: 38 | B39: Epic | C39: Flow Composition & Single-Difference Compiler | D39: Flow Composition & Single-Difference Compiler | E39: A flow binds exactly one strategy at every decision point, and the compiler refuses to build a variant that differs from its baseline at more than one. | G39: P0 | J39: R2 | K39: O2 | L39: D60 | M39: Control Plane | N39: Payments Platform
A40: 39 | B40: Story | C40: Flow Composition & Single-Difference Compiler | D40: Flow artefact schema | E40: As a strategy owner, I need a flow to name exactly one strategy at every decision point, so that there is no implicit behaviour in the path. | F40: • Schema: flow id, version, baseline reference, one binding per decision point. • An unbound decision point is a compile error, never a default. • Baseline reference is mandatory for a variant flow. | G40: P0 | H40: 5 | I40: Y | J40: R2 | K40: O2 | L40: D60 | M40: Control Plane | N40: Payments Platform | O40: Strategy artefact schema
A41: 40 | B41: Story | C41: Flow Composition & Single-Difference Compiler | D41: Flow compiler | E41: As the platform, I need flows compiled and validated before they exist in production, so that a broken flow cannot be exposed. | F41: • Compiler resolves every binding to a registered, unexpired strategy version. • Compilation fails on any unbound or unresolvable decision point. • Compiled output is deterministic — same input, same artefact. | G41: P0 | H41: 8 | I41: Y | J41: R2 | K41: O2 | L41: D60 | M41: Control Plane | N41: Payments Platform | O41: Flow artefact schema
A42: 41 | B42: Story | C42: Flow Composition & Single-Difference Compiler | D42: Single-difference check | E42: As a reviewer, I need the compiler to refuse a variant that differs from its baseline at more than one decision point, so that attribution is guaranteed rather than assumed. | F42: • Compiler computes the diff against the named baseline. • A diff count other than 1 for a variant flow is rejected with the differing points named. • Rejection cannot be overridden by a flag. | G42: P0 | H42: 8 | I42: Y | J42: R2 | K42: O2 | L42: D60 | M42: Control Plane | N42: Payments Platform | O42: Flow compiler
A43: 42 | B43: Story | C43: Flow Composition & Single-Difference Compiler | D43: Flow signing and integrity verification | E43: As the platform, I need flows cryptographically signed, so that what runs in production is what was reviewed. | F43: • Every compiled flow is signed at build. • Runtime verifies the signature before resolution and refuses an unsigned or altered flow. • Key rotation procedure documented. | G43: P0 | H43: 5 | I43: N | J43: R2 | K43: O2 | L43: D60 | M43: Control Plane | N43: Payments Platform | O43: Flow compiler
A44: 43 | B44: Story | C44: Flow Composition & Single-Difference Compiler | D44: Flow bundle distribution | E44: As the platform, I need a new flow available in every region quickly, so that promotion is not a deployment. | F44: • Bundle distributes to all regions with p99 under 60 seconds. • Distribution is observable, with per-region confirmation. • A region that fails to receive a bundle alerts and continues on last-known-good. | G44: P0 | H44: 13 | I44: Y | J44: R2 | K44: O2 | L44: D60 | M44: Control Plane | N44: Payments Platform | O44: Flow signing and integrity verification
A45: 44 | B45: Story | C45: Flow Composition & Single-Difference Compiler | D45: Regional flow resolution with last-known-good fallback | E45: As the platform, I need every region to resolve flows locally, so that a control-plane outage cannot stop authorization. | F45: • Flow resolution is local, with no synchronous control-plane call on the authorization path. • Last-known-good bundle serves if the control plane is unreachable. • Staleness is measured and alerted beyond an agreed threshold. | G45: P0 | H45: 8 | I45: Y | J45: R2 | K45: O2 | L45: D60 | M45: Control Plane | N45: Payments Platform | O45: Flow bundle distribution
A46: 45 | B46: Epic | C46: Replay & Backtest | D46: Replay & Backtest | E46: A candidate flow runs against logged decision records and produces an exact count of decisions that would change, and for whom, before any live exposure. | G46: P0 | J46: R3 | K46: O1 O4 | L46: D60 | M46: Decision Runtime | N46: Payments Platform
A47: 46 | B47: Story | C47: Replay & Backtest | D47: Replay harness | E47: As a strategy owner, I need to run a candidate flow against traffic that already happened, so that I know its blast radius before exposing anyone. | F47: • Harness replays a compiled flow against a date range of decision records. • Nothing is dispatched — no processor, network or merchant call is made. • Replay is reproducible: same flow, same window, same result. | G47: P0 | H47: 13 | I47: Y | J47: R3 | K47: O1 O4 | L47: D60 | M47: Decision Runtime | N47: Payments Platform | O47: Flow compiler
A48: 47 | B48: Story | C48: Replay & Backtest | D48: Exact changed-decision count and affected population report | E48: As a reviewer, I need to know precisely how many decisions change and for whom, so that promotion is a measured step rather than a leap. | F48: • Report gives an exact count of decisions that would differ, not an estimate. • Affected population broken down by merchant, geography and card type. • Count expressed as a percentage of eligible traffic. | G48: P0 | H48: 8 | I48: Y | J48: R3 | K48: O1 O4 | L48: D60 | M48: Decision Runtime | N48: Payments Platform | O48: Replay harness
A49: 48 | B49: Story | C49: Replay & Backtest | D49: Policy conflict detection in replay | E49: As a compliance reviewer, I need to know whether a candidate flow would violate an existing policy, so that regulatory constraints are not discovered in production. | F49: • Replay evaluates the candidate against the active policy set. • Any conflict is reported with the policy, the authority and the affected population. • A conflict blocks promotion. | G49: P0 | H49: 5 | I49: Y | J49: R3 | K49: O1 O4 | L49: D60 | M49: Decision Runtime | N49: Payments Platform | O49: Replay harness
A50: 49 | B50: Story | C50: Replay & Backtest | D50: Replay report as a promotion gate artefact | E50: As the platform, I need the replay report attached to the promotion record, so that the evidence travels with the decision. | F50: • Promotion requires a replay report against a window of at least 30 days. • Report is immutably attached to the promotion record. • A stale report, older than 14 days, is rejected. | G50: P0 | H50: 5 | I50: Y | J50: R3 | K50: O1 O4 | L50: D60 | M50: Decision Runtime | N50: Payments Platform | O50: Exact changed-decision count and affected population report
A51: 50 | B51: Story | C51: Replay & Backtest | D51: Document the replay boundary | E51: As a reviewer, I need the limits of replay stated plainly, so that nobody treats a backtest as a result. | F51: • Written statement: replay tells us which decisions would change, never whether they would have been approved. • Statement appears in the replay report itself, not only in a wiki. • Replay output is never merged with experiment output in any report. | G51: P0 | H51: 2 | I51: Y | J51: R3 | K51: O1 O4 | L51: D60 | M51: Decision Runtime | N51: Payments Platform | O51: Replay harness
A52: 51 | B52: Epic | C52: Experiment Registration & Mechanical Gates | D52: Experiment Registration & Mechanical Gates | E52: Registration pre-declares hypothesis, metric, effect size, direction, population, weights and stopping rule — and the gates that catch a broken design are mechanical, not a reviewer. | G52: P0 | J52: R5 | K52: O2 | L52: D60 | M52: Control Plane | N52: Experimentation
A53: 52 | B53: Story | C53: Experiment Registration & Mechanical Gates | D53: Experiment artefact schema | E53: As an experiment owner, I need to pre-declare the design, so that the result cannot be re-framed once it arrives. | F53: • Schema: hypothesis, single primary metric, effect size, direction, population predicate, arms and weights, randomisation unit, assignment point, stopping rule, guardrails. • Direction is mandatory. • Primary metric is singular — a list is rejected. | G53: P0 | H53: 5 | I53: Y | J53: R5 | K53: O2 | L53: D60 | M53: Control Plane | N53: Experimentation | O53: Strategy artefact schema
A54: 53 | B54: Story | C54: Experiment Registration & Mechanical Gates | D54: Sample-size calculator | E54: As an experiment owner, I need the duration derived from the effect size and the weights, so that experiments end on evidence rather than on a calendar. | F54: • Calculator takes baseline rate, effect size, weights, power and alpha, and returns required enrolments per arm. • Unequal allocation handled correctly — a 95/5 split is not treated as 50/50. • Output is stored on the experiment artefact and drives the stop condition. | G54: P0 | H54: 8 | I54: Y | J54: R5 | K54: O2 | L54: D60 | M54: Control Plane | N54: Experimentation | O54: Experiment artefact schema
A55: 54 | B55: Story | C55: Experiment Registration & Mechanical Gates | D55: Gate: treatment must be deliverable to the whole test arm | E55: As a reviewer, I need qualification checked against what the treatment needs, so that part of the test arm cannot silently fail to receive it. | F55: • Gate verifies that every member of the qualifying population can receive the variant treatment. • Qualification on the control credential alone is rejected when the treatment requires another. • Rejection names the unreachable sub-population. | G55: P0 | H55: 8 | I55: Y | J55: R5 | K55: O2 | L55: D60 | M55: Control Plane | N55: Experimentation | O55: Experiment artefact schema
A56: 55 | B56: Story | C56: Experiment Registration & Mechanical Gates | D56: Gate: single-difference flows only | E56: As a reviewer, I need the experiment gates to reuse the compiler check, so that there is one definition of a valid comparison. | F56: • Registration rejects an experiment whose arms differ at more than one decision point. • Gate calls the compiler diff rather than reimplementing it. | G56: P0 | H56: 3 | I56: Y | J56: R5 | K56: O2 | L56: D60 | M56: Control Plane | N56: Experimentation | O56: Single-difference check
A57: 56 | B57: Story | C57: Experiment Registration & Mechanical Gates | D57: Gate: randomisation unit appropriate to the treatment | E57: As a reviewer, I need per-transaction randomisation blocked for credential-form changes, so that we do not create the risk signal we are trying to measure. | F57: • Gate rejects per-transaction randomisation where the treatment changes credential form or authentication behaviour. • Rejection explains the issuer-behaviour reason. • Customer-level and merchant-level units supported. | G57: P0 | H57: 5 | I57: Y | J57: R5 | K57: O2 | L57: D60 | M57: Control Plane | N57: Experimentation | O57: Experiment artefact schema
A58: 57 | B58: Story | C58: Experiment Registration & Mechanical Gates | D58: Gate: pre-registration lock | E58: As a reviewer, I need the design frozen once traffic moves, so that the hypothesis cannot follow the data. | F58: • No field on the experiment artefact is editable after the first enrolment, except exposure weights within the pre-declared ramp. • An attempted edit is rejected and audited. • Amendments require a new experiment with a stated relationship to the original. | G58: P0 | H58: 5 | I58: Y | J58: R5 | K58: O2 | L58: D60 | M58: Control Plane | N58: Experimentation | O58: Experiment artefact schema
A59: 58 | B59: Story | C59: Experiment Registration & Mechanical Gates | D59: Allocation ledger | E59: As the platform, I need one active experiment per layer and segment, so that two experiments cannot silently contaminate each other. | F59: • Ledger records every active experiment against a controlled segment vocabulary. • Registering a second experiment on an occupied (layer, segment) is rejected with the conflicting experiment named. • Ledger is queryable and reported weekly. | G59: P0 | H59: 8 | I59: Y | J59: R5 | K59: O2 | L59: D60 | M59: Control Plane | N59: Experimentation | O59: Experiment artefact schema
A60: 59 | B60: Epic | C60: Registry Build & Processor Verification | D60: Registry Build & Processor Verification | E60: The decision-point and capability registries built and verified with processors rather than asserted, and enforced as a capability filter at decision time. | G60: P0 | J60: R1 | K60: O5 | L60: D60 | M60: Architecture | N60: Architecture
A61: 60 | B61: Story | C61: Registry Build & Processor Verification | D61: Build the decision-point registry | E61: As the platform, I need the decision points registered rather than implied by code, so that a strategy can be bound to one without an engineering change. | F61: • Registry built to the agreed schema, bitemporal. • All five current decision points registered. • Adding a decision point is a registry change, not a code change. | G61: P0 | H61: 8 | I61: Y | J61: R1 | K61: O5 | L61: D60 | M61: Architecture | N61: Architecture | O61: Publish the registry scope decision for sign-off
A62: 61 | B62: Story | C62: Registry Build & Processor Verification | D62: Build the capability registry | E62: As the platform, I need to know what each route can actually support, so that a strategy cannot choose an option that will fail. | F62: • Registry built to the agreed capability model. • Capabilities carry a source and an expiry. • An expired capability fact degrades to unsupported rather than to assumed-supported. | G62: P0 | H62: 8 | I62: Y | J62: R1 | K62: O5 | L62: D60 | M62: Architecture | N62: Architecture | O62: Define the capability model
A63: 62 | B63: Story | C63: Registry Build & Processor Verification | D63: Verify capability data with processors | E63: As an architect, I need capabilities verified rather than asserted, so that the capability filter is trustworthy. | F63: • Each processor capability confirmed with the processor or by controlled test. • Unverifiable facts marked as asserted, with an expiry and an owner. • Verification status visible in the registry and in any trace that used it. | G63: P0 | H63: 13 | I63: N | J63: R1 | K63: O5 | L63: D60 | M63: Architecture | N63: Architecture | O63: Build the capability registry
A64: 63 | B64: Story | C64: Registry Build & Processor Verification | D64: Enforce the capability filter at decision time | E64: As the platform, I need unsupported options removed before a strategy chooses, so that a strategy never has to know about downstream limits. | F64: • Capability filter runs ahead of strategy evaluation at every decision point. • Filtered-out options appear in the decision record as not-permitted, with the reason. • Filter adds under 1ms at p99. | G64: P0 | H64: 8 | I64: Y | J64: R1 | K64: O5 | L64: D60 | M64: Architecture | N64: Architecture | O64: Build the capability registry
A65: 64 | B65: Epic | C65: Assignment & Exposure Control | D65: Assignment & Exposure Control | E65: Promotion is decoupled from exposure, assignment is deterministic at the divergence point, and traffic moves by changing a number rather than by a deployment. | G65: P0 | J65: R4 R6 | K65: O2 O4 | L65: D90 | M65: Decision Runtime | N65: Payments Platform
A66: 65 | B66: Story | C66: Assignment & Exposure Control | D66: Promotion decoupled from exposure | E66: As a strategy owner, I need a flow to reach production at zero percent, so that promotion is safe and reversible by construction. | F66: • A promoted flow is resolvable in every region and receives no traffic until an exposure record says so. • A flow can sit at 0% indefinitely without expiring. • Promotion changes no merchant behaviour and requires no deployment window. | G66: P0 | H66: 5 | I66: Y | J66: R4 | K66: O2 O4 | L66: D90 | M66: Decision Runtime | N66: Payments Platform | O66: Regional flow resolution with last-known-good fallback
A67: 66 | B67: Story | C67: Assignment & Exposure Control | D67: Deterministic assignment at the divergence point | E67: As an analyst, I need assignment to happen at the last node common to all arms, so that transactions that could never receive the treatment are not diluting the measurement. | F67: • Assignment occurs immediately before the first differing decision point, not at context assembly. • Assignment is deterministic on the randomisation unit — same unit, same arm, for the life of the experiment. • Transactions that never reach the divergence point are not enrolled. | G67: P0 | H67: 13 | I67: Y | J67: R6 | K67: O2 O4 | L67: D90 | M67: Decision Runtime | N67: Payments Platform | O67: Allocation ledger
A68: 67 | B68: Story | C68: Assignment & Exposure Control | D68: Carry assignment across retries | E68: As an analyst, I need every attempt in a transaction to stay in the same arm, so that a retry cannot cross arms and corrupt the result. | F68: • All attempts within a transaction resolve to the assigned arm. • Assignment is recorded on the first attempt and reused, never recomputed. • A cross-arm retry is impossible by construction, and any occurrence alerts. | G68: P0 | H68: 8 | I68: Y | J68: R6 | K68: O2 O4 | L68: D90 | M68: Decision Runtime | N68: Payments Platform | O68: Deterministic assignment at the divergence point
A69: 68 | B69: Story | C69: Assignment & Exposure Control | D69: Runtime exposure weight changes | E69: As an experiment owner, I need to change exposure by changing a number, so that ramping and stopping do not require a release. | F69: • Weights changeable at runtime, taking effect within one propagation cycle. • Change is audited with actor, time and prior value. • Weights cannot be moved outside the pre-declared ramp without a documented override. | G69: P0 | H69: 8 | I69: Y | J69: R4 | K69: O2 O4 | L69: D90 | M69: Decision Runtime | N69: Payments Platform | O69: Promotion decoupled from exposure
A70: 69 | B70: Story | C70: Assignment & Exposure Control | D70: Treatment fidelity tracking | E70: As an analyst, I need transactions that fell back to stay in their assigned arm but be flagged, so that intent-to-treat and per-protocol can both be reported. | F70: • A transaction that could not receive its assigned treatment remains in its arm and is flagged. • Fidelity rate computed per arm and reported live. • A fidelity floor is enforced as a promotion gate. | G70: P0 | H70: 8 | I70: Y | J70: R6 | K70: O2 O4 | L70: D90 | M70: Decision Runtime | N70: Payments Platform | O70: Carry assignment across retries
A71: 70 | B71: Story | C71: Assignment & Exposure Control | D71: Exposure authority controls and audit trail | E71: As the platform owner, I need exposure changes restricted to named roles, so that traffic does not move without accountability. | F71: • Only holders of the exposure authority role may change weights. • Every change is audited and visible in the experiment record. • Emergency abort is available to on-call without the full role. | G71: P0 | H71: 5 | I71: N | J71: R4 | K71: O2 O4 | L71: D90 | M71: Decision Runtime | N71: Payments Platform | O71: Runtime exposure weight changes
A72: 71 | B72: Epic | C72: Live Monitoring & Automatic Guardrail Abort | D72: Live Monitoring & Automatic Guardrail Abort | E72: Exposure, pace and guardrails visible in real time, with an arm removed from allocation automatically within one propagation cycle on breach. | G72: P0 | J72: R9 | K72: O4 | L72: D90 | M72: Observability | N72: Experimentation
A73: 72 | B73: Story | C73: Live Monitoring & Automatic Guardrail Abort | D73: Real-time enrolment and exposure dashboard | E73: As an experiment owner, I need to see enrolment pace against the target, so that a stalled or runaway experiment is visible immediately. | F73: • Dashboard shows qualifying volume, per-arm enrolment, actual vs target share, and projected days to sample size. • Refresh under five minutes. • Available to the review forum without a request. | G73: P0 | H73: 8 | I73: Y | J73: R9 | K73: O4 | L73: D90 | M73: Observability | N73: Experimentation | O73: Deterministic assignment at the divergence point
A74: 73 | B74: Story | C74: Live Monitoring & Automatic Guardrail Abort | D74: Guardrail metric computation | E74: As an experiment owner, I need guardrails computed continuously, so that harm is detected in hours rather than at readout. | F74: • Computes approval gap, fraud proxy, dispute proxy, cost of acceptance, per-merchant harm and latency, per arm. • Each guardrail has a declared threshold on the experiment artefact. • Computation lag under 30 minutes. | G74: P0 | H74: 13 | I74: Y | J74: R9 | K74: O4 | L74: D90 | M74: Observability | N74: Experimentation | O74: Real-time enrolment and exposure dashboard
A75: 74 | B75: Story | C75: Live Monitoring & Automatic Guardrail Abort | D75: Automatic arm abort on breach | E75: As the platform owner, I need a breaching arm removed from allocation without a human in the path, so that the blast radius is bounded by the system rather than by a meeting. | F75: • A guardrail breach removes the arm from allocation within one propagation cycle. • Abort requires no approval and cannot be blocked. • Aborted arms cannot be re-enabled without a documented review. | G75: P0 | H75: 13 | I75: Y | J75: R9 | K75: O4 | L75: D90 | M75: Observability | N75: Experimentation | O75: Guardrail metric computation
A76: 75 | B76: Story | C76: Live Monitoring & Automatic Guardrail Abort | D76: Abort floor on the effect itself | E76: As the platform owner, I need an experiment to stop if the effect is far worse than expected, so that a deliberately weaker arm cannot run away. | F76: • An effect-size floor is declared on the experiment artefact alongside the guardrails. • Breaching the floor aborts the arm on the same path as a guardrail breach. • Floor is mandatory for any experiment whose declared direction is negative. | G76: P0 | H76: 5 | I76: Y | J76: R9 | K76: O4 | L76: D90 | M76: Observability | N76: Experimentation | O76: Automatic arm abort on breach
A77: 76 | B77: Story | C77: Live Monitoring & Automatic Guardrail Abort | D77: Per-merchant harm detection | E77: As Client Service, I need to know if the cost of an experiment is concentrating on one merchant, so that a portfolio-level pass does not hide an individual loss. | F77: • Guardrails evaluated per merchant as well as in aggregate. • A merchant breaching individually is removed from the experiment without aborting it entirely. • Client Service is notified with the merchant and the measured impact. | G77: P0 | H77: 8 | I77: Y | J77: R9 | K77: O4 | L77: D90 | M77: Observability | N77: Experimentation | O77: Guardrail metric computation
A78: 77 | B78: Story | C78: Live Monitoring & Automatic Guardrail Abort | D78: Abort notification and post-abort report | E78: As the review forum, I need to know immediately when an arm aborts and why, so that the next decision is informed. | F78: • Abort notifies the experiment owner, the platform owner and Client Service within five minutes. • Post-abort report states the breached guardrail, the measured value, the affected population and the exposure at abort. • Report attached to the experiment record. | G78: P1 | H78: 5 | I78: N | J78: R9 | K78: O4 | L78: D90 | M78: Observability | N78: Experimentation | O78: Automatic arm abort on breach
A79: 78 | B79: Epic | C79: Decision Trace | D79: Decision Trace | E79: Any transaction explained end to end — experiment membership, arm, flow, every decision applied and what the baseline would have decided — self-serve, in under two minutes. | G79: P0 | J79: R10 | K79: O5 | L79: D90 | M79: Observability | N79: Experimentation
A80: 79 | B80: Story | C80: Decision Trace | D80: Per-transaction decision trace API | E80: As support and product, I need to retrieve every decision applied to a transaction, so that explaining an outcome does not require an engineer. | F80: • API returns, for a transaction: experiment membership, arm, flow and version, every decision point with the strategy applied, the action chosen and the fallback that would have fired. • Response under two seconds at p95. • Available for any transaction within the retention window. | G80: P0 | H80: 8 | I80: Y | J80: R10 | K80: O5 | L80: D90 | M80: Observability | N80: Experimentation | O80: Persist decision records with 13-month retention
A81: 80 | B81: Story | C81: Decision Trace | D81: Self-serve trace UI | E81: As support, I need to answer "why did this transaction do that" myself, so that explanations are not an escalation. | F81: • A non-engineer can go from transaction id to full explanation in under two minutes. • Tested with five users from Client Service, unassisted. • Links to the strategy and flow artefacts that were in force. | G81: P1 | H81: 13 | I81: N | J81: R10 | K81: O5 | L81: D90 | M81: Observability | N81: Experimentation | O81: Per-transaction decision trace API
A82: 81 | B82: Story | C82: Decision Trace | D82: Trace shows experiment membership and propensity | E82: As an analyst, I need membership and propensity visible per transaction, so that an individual case can be reconciled against the aggregate. | F82: • Trace shows in-experiment yes/no, experiment name, arm, assignment unit, assignment point, propensity and treatment-delivered flag. • Fields match the decision record exactly — no re-derivation. | G82: P0 | H82: 5 | I82: Y | J82: R10 | K82: O5 | L82: D90 | M82: Observability | N82: Experimentation | O82: Per-transaction decision trace API
A83: 82 | B83: Story | C83: Decision Trace | D83: Trace shows the counterfactual per decision point | E83: As an analyst, I need the "would have" column in the trace, so that attribution is inspectable at the individual level. | F83: • For each decision point, trace shows the action chosen and the action the baseline flow would have chosen. • The trace states plainly that this is what would have been decided, not what would have been approved. | G83: P0 | H83: 5 | I83: Y | J83: R10 | K83: O5 | L83: D90 | M83: Observability | N83: Experimentation | O83: Per-transaction decision trace API
A84: 83 | B84: Story | C84: Decision Trace | D84: Access control and PCI scope review for trace data | E84: As compliance, I need trace access governed, so that a debugging tool does not become a data exposure. | F84: • Role-based access defined and implemented. • PCI scope assessment completed and signed off. • Credential values shown as tokens or last-four only; access to full values is separately controlled and audited. | G84: P0 | H84: 8 | I84: Y | J84: R10 | K84: O5 | L84: D90 | M84: Observability | N84: Experimentation | O84: Per-transaction decision trace API
A85: 84 | B85: Epic | C85: Outcome Join & Economic Readout | D85: Outcome Join & Economic Readout | E85: Outcomes joined at four horizons, revised as later horizons land, and translated into merchant and PSP economics by pricing model. | G85: P0 | J85: R11 R12 | K85: O2 | L85: D90 | M85: Analytics | N85: Analytics Engineering
A86: 85 | B86: Story | C86: Outcome Join & Economic Readout | D86: Outcome join at four horizons | E86: As an analyst, I need decisions joined to outcomes as they land, so that a readout is not limited to what is known at authorization. | F86: • Joins at authorization, settlement, 30-day fraud and 120-day dispute. • Each readout states which horizons are complete and which are pending. • Join is idempotent and reproducible. | G86: P0 | H86: 13 | I86: Y | J86: R11 | K86: O2 | L86: D90 | M86: Analytics | N86: Analytics Engineering | O86: Verify record completeness against transaction volume
A87: 86 | B87: Story | C87: Outcome Join & Economic Readout | D87: Readout revision as later horizons land | E87: As a decision maker, I need readouts revised rather than replaced, so that a conclusion drawn at 30 days is visibly superseded at 120. | F87: • Each readout is versioned with the horizons it covers. • A later revision links to the one it supersedes and states what changed. • Prior revisions remain retrievable. | G87: P0 | H87: 8 | I87: Y | J87: R11 | K87: O2 | L87: D90 | M87: Analytics | N87: Analytics Engineering | O87: Outcome join at four horizons
A88: 87 | B88: Story | C88: Outcome Join & Economic Readout | D88: Scorecard computation | E88: As a decision maker, I need approval reported alongside cost, fraud, dispute and fidelity, so that no readout can present approval alone. | F88: • Scorecard computes transaction approval, first-attempt approval, cost of acceptance, fraud proxy, dispute proxy and treatment fidelity. • A scorecard with a missing dimension is not publishable. • Each line shows control, variant, delta and status. | G88: P0 | H88: 8 | I88: Y | J88: R12 | K88: O2 | L88: D90 | M88: Analytics | N88: Analytics Engineering | O88: Outcome join at four horizons
A89: 88 | B89: Story | C89: Outcome Join & Economic Readout | D89: Confidence intervals and stopping-rule evaluation | E89: As a decision maker, I need an interval rather than a point estimate, so that a result is reported with its uncertainty. | F89: • Confidence interval computed for every primary and guardrail metric. • Stopping rule evaluated against the pre-declared sample size, never against the observed effect. • Peeking is prevented or explicitly corrected, and which was done is stated. | G89: P0 | H89: 8 | I89: Y | J89: R12 | K89: O2 | L89: D90 | M89: Analytics | N89: Analytics Engineering | O89: Scorecard computation
A90: 89 | B90: Story | C90: Outcome Join & Economic Readout | D90: Economic translation by pricing model | E90: As Product and Finance, I need the result in money, so that the decision is commercial rather than statistical. | F90: • Translates the measured effect into merchant margin and PSP net revenue, separately for interchange-plus and blended pricing. • Assumptions (margin rate, take rate) are named inputs, not constants in code. • Output shows the exchange rate: bps of cost per 100 bps of approval. | G90: P0 | H90: 8 | I90: Y | J90: R12 | K90: O2 | L90: D90 | M90: Analytics | N90: Analytics Engineering | O90: Confidence intervals and stopping-rule evaluation
A91: 90 | B91: Story | C91: Outcome Join & Economic Readout | D91: Publish the readout with a date and an expiry | E91: As the platform owner, I need every published number to carry an expiry, so that a measurement does not quietly become a claim. | F91: • Readout is published with the measurement window, the baseline version and an expiry date. • An expired readout is flagged wherever it is cited. • Re-run cadence recorded on the readout. | G91: P0 | H91: 3 | I91: Y | J91: R12 | K91: O2 | L91: D90 | M91: Analytics | N91: Analytics Engineering | O91: Economic translation by pricing model
A92: 91 | B92: Epic | C92: Promotion & Baseline Ratchet | D92: Promotion & Baseline Ratchet | E92: A winner promotes to a named population, the baseline recompiles with it bound in, and rollback is an exposure pointer change. | G92: P0 | J92: R13 | K92: O2 O4 | L92: D90 | M92: Control Plane | N92: Payments Platform
A93: 92 | B93: Story | C93: Promotion & Baseline Ratchet | D93: Scoped promotion | E93: As a strategy owner, I need to promote a winner to a named population rather than globally, so that a result that holds for one segment is not applied to all. | F93: • Promotion targets a declared population, using the same predicate vocabulary as the experiment. • Promotion outside the tested population requires a documented justification. • Promotion record links to the readout that justified it. | G93: P0 | H93: 8 | I93: Y | J93: R13 | K93: O2 O4 | L93: D90 | M93: Control Plane | N93: Payments Platform | O93: Publish the readout with a date and an expiry
A94: 93 | B94: Story | C94: Promotion & Baseline Ratchet | D94: Baseline recompile with the winner bound in | E94: As the platform, I need the baseline to move when a variant wins, so that the next experiment measures against the current best. | F94: • A new baseline flow version is compiled with the winning strategy bound at the relevant decision point. • The prior baseline remains resolvable for historical traces. • Active experiments against the old baseline are flagged for re-baselining. | G94: P0 | H94: 8 | I94: Y | J94: R13 | K94: O2 O4 | L94: D90 | M94: Control Plane | N94: Payments Platform | O94: Scoped promotion
A95: 94 | B95: Story | C95: Promotion & Baseline Ratchet | D95: Rollback as an exposure pointer change | E95: As on-call, I need to reverse a promotion without a deployment, so that reversal is measured in minutes. | F95: • Rollback changes an exposure pointer only — no deploy, no data migration. • Takes effect within one propagation cycle. • Rehearsed in a game day before D90 exit. | G95: P0 | H95: 3 | I95: Y | J95: R13 | K95: O2 O4 | L95: D90 | M95: Control Plane | N95: Payments Platform | O95: Baseline recompile with the winner bound in
A96: 95 | B96: Story | C96: Promotion & Baseline Ratchet | D96: Evidence record | E96: As the platform owner, I need every readout retained against its baseline version, so that cumulative value can be reconstructed later. | F96: • Every readout stored with the baseline version it measured against, the population and the date. • Record is append-only. • Queryable to answer: what has this platform been worth since inception. | G96: P1 | H96: 5 | I96: N | J96: R13 | K96: O2 O4 | L96: D90 | M96: Control Plane | N96: Payments Platform | O96: Baseline recompile with the winner bound in
A97: 96 | B97: Epic | C97: Experiment 1 — Credential (execution) | D97: Experiment 1 — Credential (execution) | E97: Run the first controlled experiment end to end: vault network token as control, merchant-supplied credential as the deliberately weaker variant, to an economic readout. | G97: P0 | J97: — | K97: O1 O2 O3 O4 O5 | L97: D90 | M97: Experimentation | N97: Experimentation
A98: 97 | B98: Story | C98: Experiment 1 — Credential (execution) | D98: Register Cred_MerchantSupplied_v1 | E98: As the credential product owner, I need the variant strategy registered, so that Experiment 1 has a treatment. | F98: • Strategy registered against D4.1 with population, definition, fallback Cred_VaultNetworkToken_v4, owner and 180-day expiry. • Passes all registration gates. • Reviewed by credential product and risk. | G98: P0 | H98: 3 | I98: Y | J98: — | K98: O1 O2 O3 O4 O5 | L98: D90 | M98: Experimentation | N98: Experimentation | O98: Strategy registration API and CLI
A99: 98 | B99: Story | C99: Experiment 1 — Credential (execution) | D99: Compose F3_MerchantCred_v1 from F2_VaultNWT_v6 | E99: As the experiment owner, I need a variant flow that differs from the baseline at exactly one point, so that the result is attributable. | F99: • Flow compiles with diff_count = 1 against F2_VaultNWT_v6. • Every other binding identical to the baseline. • Flow signed and distributed to all regions at 0% exposure. | G99: P0 | H99: 3 | I99: Y | J99: — | K99: O1 O2 O3 O4 O5 | L99: D90 | M99: Experimentation | N99: Experimentation | O99: Single-difference check
A100: 99 | B100: Story | C100: Experiment 1 — Credential (execution) | D100: Backtest and publish the blast-radius report | E100: As the review forum, I need the exact number of decisions that would change before any exposure, so that promotion is an informed step. | F100: • Replay against at least 30 days of decision records. • Report gives exact changed-decision count, percentage of eligible traffic and affected merchants. • No policy conflicts introduced. | G100: P0 | H100: 5 | I100: Y | J100: — | K100: O1 O2 O3 O4 O5 | L100: D90 | M100: Experimentation | N100: Experimentation | O100: Replay report as a promotion gate artefact
...

Sheet Epics
A1: Epic Key | B1: Epic Name | C1: Horizon | D1: Objective | E1: Requirement | F1: Component | G1: Owning Team | H1: Stories | I1: Points | J1: Critical Pts | K1: Epic Goal
A2: DP-1 | B2: Decision Evidence Layer | C2: D30 | D2: O3 | E2: R8 | F2: Decision Runtime | G2: Payments Platform | H2: =COUNTIFS(Backlog!$C:$C,$B2,Backlog!$B:$B,"<>Epic") -> 10 | I2: =SUMIFS(Backlog!$H:$H,Backlog!$C:$C,$B2) -> 53 | J2: =SUMIFS(Backlog!$H:$H,Backlog!$C:$C,$B2,Backlog!$I:$I,"Y") -> 50 | K2: Every eligible decision on the CURRENT engine emits what was chosen, what else was permitted, the probability assigned, and what the fallback would have done. This is the one capability that cannot be backfilled.
A3: DP-2 | B3: Permanent Platform Holdout | C3: D30 | D3: O2 O3 | E3: R7 | F3: Decision Runtime | G3: Payments Platform | H3: =COUNTIFS(Backlog!$C:$C,$B3,Backlog!$B:$B,"<>Epic") -> 6 | I3: =SUMIFS(Backlog!$H:$H,Backlog!$C:$C,$B3) -> 23 | J3: =SUMIFS(Backlog!$H:$H,Backlog!$C:$C,$B3,Backlog!$I:$I,"Y") -> 16 | K3: A 2% population reserved before the first experiment runs, excluded from experiments and from exploration, with a creation date that cannot be edited.
A4: DP-3 | B4: Decision-Point & Capability Registry — Definition | C4: D30 | D4: O1 O5 | E4: R1 | F4: Architecture | G4: Architecture | H4: =COUNTIFS(Backlog!$C:$C,$B4,Backlog!$B:$B,"<>Epic") -> 5 | I4: =SUMIFS(Backlog!$H:$H,Backlog!$C:$C,$B4) -> 20 | J4: =SUMIFS(Backlog!$H:$H,Backlog!$C:$C,$B4,Backlog!$I:$I,"Y") -> 20 | K4: Agree what the decision points are, what each may choose from, and what a route can actually support. Scope and schema only — the build is D60.
A5: DP-4 | B5: Operating Model & Ownership | C5: D30 | D5: O1 O4 | E5: — | F5: Governance | G5: Product | H5: =COUNTIFS(Backlog!$C:$C,$B5,Backlog!$B:$B,"<>Epic") -> 5 | I5: =SUMIFS(Backlog!$H:$H,Backlog!$C:$C,$B5) -> 19 | J5: =SUMIFS(Backlog!$H:$H,Backlog!$C:$C,$B5,Backlog!$I:$I,"Y") -> 16 | K5: The five ownership boundaries named, the exploration budget bounded, the economic objective expressed in a usable form, and the consent posture settled.
A6: DP-5 | B6: Strategy Registry & Artefact Lifecycle | C6: D60 | D6: O1 O4 | E6: R1 R14 | F6: Control Plane | G6: Payments Platform | H6: =COUNTIFS(Backlog!$C:$C,$B6,Backlog!$B:$B,"<>Epic") -> 6 | I6: =SUMIFS(Backlog!$H:$H,Backlog!$C:$C,$B6) -> 30 | J6: =SUMIFS(Backlog!$H:$H,Backlog!$C:$C,$B6,Backlog!$I:$I,"Y") -> 23 | K6: A strategy becomes a registered, versioned artefact with an owner, a fallback and an expiry — deployable without an engineering release.
A7: DP-6 | B7: Flow Composition & Single-Difference Compiler | C7: D60 | D7: O2 | E7: R2 | F7: Control Plane | G7: Payments Platform | H7: =COUNTIFS(Backlog!$C:$C,$B7,Backlog!$B:$B,"<>Epic") -> 6 | I7: =SUMIFS(Backlog!$H:$H,Backlog!$C:$C,$B7) -> 47 | J7: =SUMIFS(Backlog!$H:$H,Backlog!$C:$C,$B7,Backlog!$I:$I,"Y") -> 42 | K7: A flow binds exactly one strategy at every decision point, and the compiler refuses to build a variant that differs from its baseline at more than one.
A8: DP-7 | B8: Replay & Backtest | C8: D60 | D8: O1 O4 | E8: R3 | F8: Decision Runtime | G8: Payments Platform | H8: =COUNTIFS(Backlog!$C:$C,$B8,Backlog!$B:$B,"<>Epic") -> 5 | I8: =SUMIFS(Backlog!$H:$H,Backlog!$C:$C,$B8) -> 33 | J8: =SUMIFS(Backlog!$H:$H,Backlog!$C:$C,$B8,Backlog!$I:$I,"Y") -> 33 | K8: A candidate flow runs against logged decision records and produces an exact count of decisions that would change, and for whom, before any live exposure.
A9: DP-8 | B9: Experiment Registration & Mechanical Gates | C9: D60 | D9: O2 | E9: R5 | F9: Control Plane | G9: Experimentation | H9: =COUNTIFS(Backlog!$C:$C,$B9,Backlog!$B:$B,"<>Epic") -> 7 | I9: =SUMIFS(Backlog!$H:$H,Backlog!$C:$C,$B9) -> 42 | J9: =SUMIFS(Backlog!$H:$H,Backlog!$C:$C,$B9,Backlog!$I:$I,"Y") -> 42 | K9: Registration pre-declares hypothesis, metric, effect size, direction, population, weights and stopping rule — and the gates that catch a broken design are mechanical, not a reviewer.
A10: DP-9 | B10: Registry Build & Processor Verification | C10: D60 | D10: O5 | E10: R1 | F10: Architecture | G10: Architecture | H10: =COUNTIFS(Backlog!$C:$C,$B10,Backlog!$B:$B,"<>Epic") -> 4 | I10: =SUMIFS(Backlog!$H:$H,Backlog!$C:$C,$B10) -> 37 | J10: =SUMIFS(Backlog!$H:$H,Backlog!$C:$C,$B10,Backlog!$I:$I,"Y") -> 24 | K10: The decision-point and capability registries built and verified with processors rather than asserted, and enforced as a capability filter at decision time.
A11: DP-10 | B11: Assignment & Exposure Control | C11: D90 | D11: O2 O4 | E11: R4 R6 | F11: Decision Runtime | G11: Payments Platform | H11: =COUNTIFS(Backlog!$C:$C,$B11,Backlog!$B:$B,"<>Epic") -> 6 | I11: =SUMIFS(Backlog!$H:$H,Backlog!$C:$C,$B11) -> 47 | J11: =SUMIFS(Backlog!$H:$H,Backlog!$C:$C,$B11,Backlog!$I:$I,"Y") -> 42 | K11: Promotion is decoupled from exposure, assignment is deterministic at the divergence point, and traffic moves by changing a number rather than by a deployment.
A12: DP-11 | B12: Live Monitoring & Automatic Guardrail Abort | C12: D90 | D12: O4 | E12: R9 | F12: Observability | G12: Experimentation | H12: =COUNTIFS(Backlog!$C:$C,$B12,Backlog!$B:$B,"<>Epic") -> 6 | I12: =SUMIFS(Backlog!$H:$H,Backlog!$C:$C,$B12) -> 52 | J12: =SUMIFS(Backlog!$H:$H,Backlog!$C:$C,$B12,Backlog!$I:$I,"Y") -> 47 | K12: Exposure, pace and guardrails visible in real time, with an arm removed from allocation automatically within one propagation cycle on breach.
A13: DP-12 | B13: Decision Trace | C13: D90 | D13: O5 | E13: R10 | F13: Observability | G13: Experimentation | H13: =COUNTIFS(Backlog!$C:$C,$B13,Backlog!$B:$B,"<>Epic") -> 5 | I13: =SUMIFS(Backlog!$H:$H,Backlog!$C:$C,$B13) -> 39 | J13: =SUMIFS(Backlog!$H:$H,Backlog!$C:$C,$B13,Backlog!$I:$I,"Y") -> 26 | K13: Any transaction explained end to end — experiment membership, arm, flow, every decision applied and what the baseline would have decided — self-serve, in under two minutes.
... A17: DP-16 | B17: Credential Seasoning (enables Experiment 2) | C17: D90+ | D17: O2 | E17: R15 | F17: Credential Vault | G17: Credential Vault | H17: =COUNTIFS(Backlog!$C:$C,$B17,Backlog!$B:$B,"<>Epic") -> 4 | I17: =SUMIFS(Backlog!$H:$H,Backlog!$C:$C,$B17) -> 34 | J17: =SUMIFS(Backlog!$H:$H,Backlog!$C:$C,$B17,Backlog!$I:$I,"Y") -> 34 | K17: Provisioning decoupled from presentation so a treatment seasons before exposure — without this, Experiment 2 measures a freshly minted token rather than the vault.

Sheet Risks & Dependencies
A1: ID | B1: Type | C1: Risk | D1: Detail | E1: Status | F1: Owner
A2: R-1 | B2: Capacity | C2: The 90-day plan is not fundable from a single squad | D2: D30 to D90 totals well above what two squads deliver in six sprints. Either resource to three squads or cut scope against the Critical To Outcome column. | E2: Open | F2: Product · Platform
A3: R-2 | B3: Legal | C3: Exploration consent may block Experiment 1 at the last gate | D3: A knowingly weaker arm on a named client may require contractual consent that existing agreements do not cover. Consent work is on the D30 critical path for that reason. | E3: Open | F3: Legal · Client Service
A4: R-3 | B4: Methodology | C4: Assignment at the wrong point silently dilutes the result | D4: If assignment happens at context assembly rather than at the divergence point, transactions that could never receive the treatment enter the variant arm and depress the measured effect. DP-10 must land before any live exposure. | E4: Mitigated by DP-10 | F4: Payments Platform
A5: R-4 | B5: Methodology | C5: Token seasoning confounds Experiment 2 | D5: Provisioning only the variant cohort at experiment start measures new-token performance, not vault performance, and understates the vault. DP-16 must precede Experiment 2. | E5: Mitigated by DP-16 | F5: Credential Vault
A6: R-5 | B6: Data | C6: Decision-record completeness below 99.5% invalidates readouts | D6: A silent drop in emission biases the measured population. Reconciliation (DP-1) is a gate on every readout, not a nice-to-have. | E6: Mitigated by DP-1 | F6: Payments Platform
A7: R-6 | B7: Latency | C7: Evidence-layer emission adds latency to the authorization path | D7: Fallback shadow resolution and record emission both sit near the critical path. The SPIKE in DP-1 determines synchronous vs asynchronous, and that choice trades latency against completeness. | E7: Open | F7: Payments Platform
A8: R-7 | B8: Compliance | C8: Trace data may expand PCI scope | D8: Decision traces reference credential selection. Scope assessment is inside DP-12 and must complete before the trace UI is exposed beyond engineering. | E8: Open | F8: Compliance · Platform
A9: R-8 | B9: Commercial | C9: Blended-pricing merchants make the vault a cost to us | D9: If Experiment 1 confirms the exchange rate, the economics differ by pricing model and a pricing decision follows. This is an outcome of the plan, not a risk to it — but it needs an owner before the readout lands. | E9: Open | F9: Product · Finance
A10: R-9 | B10: Scope | C10: Registry verification with processors is externally dependent | D10: DP-9 processor verification depends on third-party responsiveness and cannot be compressed by adding people. Treat asserted-with-expiry as the fallback. | E10: Open | F10: Architecture
A11: R-10 | B11: Governance | C11: Holdout erosion under delivery pressure | D11: A 2% holdout is a standing temptation to reclaim. The non-resizable policy (DP-2) exists because this is the most likely quiet failure of the platform. | E11: Mitigated by DP-2 | F11: Product

Sheet Definition of Done
A1: Definition of Done — per horizon
A2: A horizon is complete when its criterion can be demonstrated, not when its stories are closed.
A4: By Day 30 | B4: We can reconstruct every eligible decision and its counterfactual.
B5: ☐ Pick any transaction from the last 30 days. Show what was chosen at D4.1, D4.2 and D6, what else was permitted, the propensity, and what the fallback would have done.
B6: ☐ Decision-record completeness is at or above 99.5% against eligible transaction volume, evidenced by the daily reconciliation.
B7: ☐ The 2% holdout exists, has an immutable creation date that pre-dates every experiment, and is excluded from both experiments and exploration.
B8: ☐ Five ownership boundaries have named owners who have confirmed in writing.
B9: ☐ The economic objective is expressed as an exchange rate, with a value for interchange-plus and a value for blended pricing.
B10: ☐ Registry scope is signed off by Architecture — not built, agreed.
A12: By Day 60 | B12: We can register, replay and validate a strategy without a release.
B13: ☐ Register a new strategy and compose a variant flow, end to end, with no engineering release and no deployment window.
B14: ☐ The compiler rejects a variant that differs from its baseline at two decision points, and the rejection names both points.
B15: ☐ Replay the candidate against 30 days of logged decisions and produce an exact changed-decision count with the affected population.
B16: ☐ Register an experiment and watch the mechanical gates reject a deliberately broken design — unreachable treatment, per-transaction randomisation, occupied allocation slot.
B17: ☐ The capability filter removes unsupported options before a strategy evaluates, and the decision record shows why.
B18: ☐ Nothing in this list required a human reviewer to catch a design error.
A20: By Day 90 | B20: We have one controlled experiment running and can produce an economic readout.
B21: ☐ Experiment 1 is live, assignment happens at the divergence point, and treatment fidelity is above the declared floor.
B22: ☐ Exposure moves by changing a number; a rehearsed rollback completes within one propagation cycle.
B23: ☐ A guardrail breach removes an arm from allocation automatically, demonstrated in a game day.
B24: ☐ Any transaction can be explained end to end — membership, arm, flow, every decision, every counterfactual.
B25: ☐ A scorecard publishes with all six dimensions, confidence intervals and status. Approval alone cannot be published.
B26: ☐ The result is translated into merchant margin and PSP net revenue for both pricing models, with the exchange rate stated.
B27: ☐ The readout carries a measurement window, a baseline version and an expiry date.
B28: ☐ The review forum has recorded a promote, hold or retire decision against it.
